[
  {
    "name": "肉じゃが",
    "ジャンル": "和食",
    "加熱": true,
    "本物の食材": [
      "牛肉",
      "じゃがいも",
      "玉ねぎ",
      "にんじん",
      "糸こんにゃく"
    ],
    "使える食材カテゴリ": [
      "肉系",
      "芋系",
      "野菜系",
      "根菜系"
    ],
    "必要調理法": "煮込み",
    "加工手順": [
      "肉を一口大に",
      "じゃがいもをざく切りに",
      "にんじん・玉ねぎを適当な大きさに"
    ],
    "説明文": "醤油と砂糖で甘辛く煮込んだ日本の家庭料理の定番。ほくほくのじゃがいもに甘辛いタレが染みて、食べるとほっとする"
  },
  {
    "name": "親子丼",
    "ジャンル": "和食",
    "加熱": true,
    "本物の食材": [
      "鶏肉",
      "卵",
      "玉ねぎ",
      "ご飯"
    ],
    "使える食材カテゴリ": [
      "肉系",
      "卵系",
      "野菜系",
      "主食系"
    ],
    "必要調理法": "炒め煮",
    "加工手順": [
      "鶏肉を一口大に",
      "玉ねぎを薄切りに",
      "ご飯にのせる"
    ],
    "説明文": "鶏肉と卵を甘辛いだしで半熟に仕上げてご飯にのせた丼。とろとろの卵と鶏のうまみが絡んで、ご飯が進む安心感がある"
  },
  {
    "name": "味噌汁",
    "ジャンル": "和食",
    "加熱": true,
    "本物の食材": [
      "豆腐",
      "わかめ",
      "ねぎ"
    ],
    "使える食材カテゴリ": [
      "豆・豆腐系",
      "野菜系",
      "魚系",
      "根菜系",
      "芋系",
      "卵系"
    ],
    "必要調理法": "煮る",
    "加工手順": [
      "豆腐をさいの目に",
      "具材を適当な大きさに"
    ],
    "説明文": "だしに味噌を溶かした日本の定番汁物。具材はほぼ何でも合い、温かくて体にやさしい。毎日飲んでも飽きない懐の深さがある"
  },
  {
    "name": "きんぴらごぼう",
    "ジャンル": "和食",
    "加熱": true,
    "本物の食材": [
      "ごぼう",
      "にんじん"
    ],
    "使える食材カテゴリ": [
      "根菜系",
      "野菜系"
    ],
    "必要調理法": "炒め",
    "加工手順": [
      "ごぼうとにんじんを細切り（千切り）に"
    ],
    "説明文": "ごぼうとにんじんを醤油・砂糖・みりんで炒めたおかず。シャキシャキした食感と甘辛い香ばしさが特徴で、お弁当にもぴったり"
  },
  {
    "name": "冷奴",
    "ジャンル": "和食",
    "加熱": false,
    "本物の食材": [
      "豆腐",
      "ねぎ",
      "しょうが"
    ],
    "使える食材カテゴリ": [
      "豆・豆腐系",
      "野菜系"
    ],
    "必要調理法": "なし",
    "加工手順": [
      "豆腐を食べやすい大きさに切る",
      "ねぎを小口切りに"
    ],
    "説明文": "冷たい豆腐に薬味と醤油をかけるだけのシンプルな料理。豆腐のなめらかさと薬味のアクセントが涼しくて気持ちいい"
  },
  {
    "name": "玉子焼き",
    "ジャンル": "和食",
    "加熱": true,
    "本物の食材": [
      "卵"
    ],
    "使える食材カテゴリ": [
      "卵系"
    ],
    "必要調理法": "焼き",
    "加工手順": [
      "卵を溶きほぐして出し汁を入れる",
      "一塊になるように固めて焼く"
    ],
    "説明文": "だし入りで甘い日本の卵焼き。ふわっとした食感と優しい甘みが特徴で、お弁当にも朝食にも大活躍"
  },
  {
    "name": "ひじきの煮物",
    "ジャンル": "和食",
    "加熱": true,
    "本物の食材": [
      "ひじき",
      "油揚げ",
      "にんじん",
      "大豆"
    ],
    "使える食材カテゴリ": [
      "野菜系",
      "豆・豆腐系",
      "根菜系"
    ],
    "必要調理法": "煮る",
    "加工手順": [
      "ひじきを水で戻す",
      "にんじんを細切りに",
      "油揚げを短冊切りに"
    ],
    "説明文": "ひじきと大豆・油揚げを甘辛く煮た定番の和食惣菜。磯の風味とコクのある甘辛がご飯によく合う"
  },
  {
    "name": "ご飯のお供丼",
    "ジャンル": "和食",
    "加熱": false,
    "本物の食材": [
      "ご飯",
      "漬物"
    ],
    "使える食材カテゴリ": [
      "主食系",
      "漬物系"
    ],
    "必要調理法": "なし",
    "加工手順": [
      "漬物を適当な大きさに切る",
      "ご飯にのせる"
    ],
    "説明文": "ご飯に漬物やふりかけなどをのせて食べるシンプルな食事。手間なしで完成する、疲れた日の救世主"
  },
  {
    "name": "炊き込みご飯",
    "ジャンル": "和食",
    "加熱": true,
    "本物の食材": [
      "ご飯（米）",
      "にんじん",
      "しいたけ",
      "ごぼう",
      "鶏肉"
    ],
    "使える食材カテゴリ": [
      "主食系",
      "根菜系",
      "野菜系",
      "肉系"
    ],
    "必要調理法": "炊く",
    "加工手順": [
      "具材を細かく刻む",
      "鶏肉を小さめの一口大に",
      "全て混ぜて炊飯器に"
    ],
    "説明文": "具材をだし醤油と一緒に炊き込んだご飯。炊き上がりのいい香りと、具材の旨みが染み込んだご飯が格別"
  },
  {
    "name": "おでん",
    "ジャンル": "和食",
    "加熱": true,
    "本物の食材": [
      "大根",
      "こんにゃく",
      "ちくわ",
      "卵",
      "じゃがいも"
    ],
    "使える食材カテゴリ": [
      "根菜系",
      "芋系",
      "卵系",
      "魚系"
    ],
    "必要調理法": "煮込み",
    "加工手順": [
      "大根を2〜3cm厚の輪切りに",
      "具材を食べやすい大きさに切る"
    ],
    "説明文": "だし汁で具材をじっくり煮込んだ冬の定番料理。だしが染みた大根や卵は格別で、体の芯から温まる"
  },
  {
    "name": "ハンバーグ",
    "ジャンル": "洋食",
    "加熱": true,
    "本物の食材": [
      "合挽き肉",
      "玉ねぎ",
      "卵",
      "パン粉"
    ],
    "使える食材カテゴリ": [
      "肉系",
      "卵系",
      "主食系"
    ],
    "必要調理法": "焼き",
    "加工手順": [
      "玉ねぎをみじん切りに",
      "全材料をよくこねて丸く成形"
    ],
    "説明文": "挽き肉を丸めて焼いた洋食の定番。肉汁がじゅわっと出てジューシー。ソースとの相性が抜群で子どもから大人まで大好き"
  },
  {
    "name": "オムライス",
    "ジャンル": "洋食",
    "加熱": true,
    "本物の食材": [
      "卵",
      "ご飯",
      "鶏肉",
      "玉ねぎ",
      "ケチャップ"
    ],
    "使える食材カテゴリ": [
      "卵系",
      "主食系",
      "肉系",
      "野菜系"
    ],
    "必要調理法": "炒め",
    "加工手順": [
      "鶏肉と玉ねぎを小さく切る",
      "ご飯と混ぜて炒める",
      "卵を溶きほぐして薄焼きにする",
      "薄焼き卵で炒めたものを包む"
    ],
    "説明文": "ケチャップライスをふわふわの卵で包んだ日本の洋食の定番。少し酸っぱいケチャップライスと優しい卵の組み合わせがクセになる"
  },
  {
    "name": "ポテトサラダ",
    "ジャンル": "洋食",
    "加熱": true,
    "本物の食材": [
      "じゃがいも",
      "にんじん",
      "きゅうり",
      "玉ねぎ",
      "ハム"
    ],
    "使える食材カテゴリ": [
      "芋系",
      "根菜系",
      "野菜系",
      "肉系"
    ],
    "必要調理法": "茹でる",
    "加工手順": [
      "じゃがいも・にんじんを茹でてつぶす",
      "きゅうりと玉ねぎを薄切りに",
      "ハムを細切りに",
      "マヨネーズと混ぜる"
    ],
    "説明文": "茹でたじゃがいもをマヨネーズで和えた定番サラダ。ほくほくのじゃがいもとクリーミーなマヨネーズが絶妙で、いくらでも食べられる"
  },
  {
    "name": "カルボナーラ",
    "ジャンル": "洋食",
    "加熱": true,
    "本物の食材": [
      "パスタ",
      "ベーコン",
      "卵",
      "粉チーズ"
    ],
    "使える食材カテゴリ": [
      "主食系",
      "肉系",
      "卵系",
      "乳製品系"
    ],
    "必要調理法": "茹でる",
    "加工手順": [
      "パスタを茹でる",
      "ベーコンを細切りに",
      "卵とチーズを混ぜてソースを作る"
    ],
    "説明文": "卵とチーズのクリーミーなソースにベーコンを合わせたパスタ。濃厚なのにしつこくなく、シンプルな材料なのに深みがある"
  },
  {
    "name": "ミネストローネ",
    "ジャンル": "洋食",
    "加熱": true,
    "本物の食材": [
      "トマト",
      "玉ねぎ",
      "にんじん",
      "セロリ",
      "じゃがいも"
    ],
    "使える食材カテゴリ": [
      "野菜系",
      "根菜系",
      "芋系"
    ],
    "必要調理法": "煮込み",
    "加工手順": [
      "全野菜を1cm角のさいの目に切る"
    ],
    "説明文": "野菜たっぷりのイタリア風スープ。トマトの酸味と野菜の甘みが溶け合って、体があったまる優しい料理"
  },
  {
    "name": "グラタン",
    "ジャンル": "洋食",
    "加熱": true,
    "本物の食材": [
      "鶏肉",
      "玉ねぎ",
      "マカロニ",
      "牛乳",
      "チーズ"
    ],
    "使える食材カテゴリ": [
      "肉系",
      "野菜系",
      "主食系",
      "乳製品系"
    ],
    "必要調理法": "焼き",
    "加工手順": [
      "鶏肉と玉ねぎを一口大に",
      "マカロニを茹でる",
      "ホワイトソースと混ぜる"
    ],
    "説明文": "ホワイトソースをかけてオーブンで焼いた温かい料理。こんがりチーズの香ばしさとクリーミーなソースが最高のご褒美感"
  },
  {
    "name": "コールスロー",
    "ジャンル": "洋食",
    "加熱": false,
    "本物の食材": [
      "キャベツ",
      "にんじん"
    ],
    "使える食材カテゴリ": [
      "野菜系",
      "根菜系"
    ],
    "必要調理法": "なし",
    "加工手順": [
      "キャベツとにんじんを千切りにする",
      "マヨネーズと混ぜる"
    ],
    "説明文": "千切り野菜をマヨネーズや酢で和えたサラダ。シャキシャキした食感と程よい酸っぱさが、こってり料理の口直しにぴったり"
  },
  {
    "name": "コーンスープ",
    "ジャンル": "洋食",
    "加熱": true,
    "本物の食材": [
      "コーン",
      "牛乳",
      "バター"
    ],
    "使える食材カテゴリ": [
      "野菜系",
      "乳製品系"
    ],
    "必要調理法": "煮る",
    "加工手順": [
      "コーンをミキサーにかける（缶詰なら不要）",
      "コーンに牛乳とバターも入れる"
    ],
    "説明文": "コーンの自然な甘みを活かしたクリーミーなスープ。飲むたびにほっこりする優しい甘さで、寒い日に特においしく感じる"
  },
  {
    "name": "フレンチトースト",
    "ジャンル": "洋食",
    "加熱": true,
    "本物の食材": [
      "食パン",
      "卵",
      "牛乳",
      "バター"
    ],
    "使える食材カテゴリ": [
      "主食系",
      "卵系",
      "乳製品系"
    ],
    "必要調理法": "焼き",
    "加工手順": [
      "卵と牛乳を混ぜて卵液を作る",
      "食パンを卵液にしっかり浸す"
    ],
    "説明文": "卵液に浸した食パンをバターで焼いた甘い朝食。外はカリッと中はふわとろで、シロップをかけると幸せな気持ちになれる"
  },
  {
    "name": "カプレーゼ",
    "ジャンル": "洋食",
    "加熱": false,
    "本物の食材": [
      "トマト",
      "モッツァレラチーズ",
      "バジル"
    ],
    "使える食材カテゴリ": [
      "野菜系",
      "乳製品系"
    ],
    "必要調理法": "なし",
    "加工手順": [
      "トマトとチーズを同じ厚さの輪切りに",
      "いい感じに交互に並べる"
    ],
    "説明文": "トマトとチーズを交互に並べたイタリアの前菜。シンプルなのに見た目が華やかで、フレッシュな素材のうまさがダイレクトに伝わる"
  },
  {
    "name": "青椒肉絲",
    "ジャンル": "中華",
    "加熱": true,
    "本物の食材": [
      "牛肉",
      "ピーマン",
      "たけのこ"
    ],
    "使える食材カテゴリ": [
      "肉系",
      "野菜系"
    ],
    "必要調理法": "炒め",
    "加工手順": [
      "肉を細切りに",
      "ピーマンとたけのこを千切りに"
    ],
    "説明文": "肉と野菜を強火で炒める中華料理の定番。シャキシャキの野菜と肉の旨みが醤油ダレに絡んで、みんな大好きな一品"
  },
  {
    "name": "麻婆豆腐",
    "ジャンル": "中華",
    "加熱": true,
    "本物の食材": [
      "豆腐",
      "豚ひき肉",
      "ねぎ",
      "にんにく",
      "しょうが"
    ],
    "使える食材カテゴリ": [
      "豆・豆腐系",
      "肉系",
      "野菜系"
    ],
    "必要調理法": "炒め煮",
    "加工手順": [
      "豆腐をさいの目に",
      "ねぎ・にんにく・しょうがをみじん切りに"
    ],
    "説明文": "豆腐と挽き肉を豆板醤でピリ辛に煮込んだ中華料理。辛さとコクがくせになり、とろとろの豆腐とピリ辛ソースで体もあったまる"
  },
  {
    "name": "チャーハン",
    "ジャンル": "中華",
    "加熱": true,
    "本物の食材": [
      "ご飯",
      "卵",
      "ねぎ",
      "チャーシュー"
    ],
    "使える食材カテゴリ": [
      "主食系",
      "卵系",
      "野菜系",
      "肉系"
    ],
    "必要調理法": "炒め",
    "加工手順": [
      "具材を細かく切る",
      "卵を溶いておく",
      "ご飯も一緒に炒める"
    ],
    "説明文": "ご飯を強火でパラパラに炒めた中華の定番。香ばしい香りとパラパラの食感が最高で、具材はなんでもおいしくなる懐の深い料理"
  },
  {
    "name": "餃子",
    "ジャンル": "中華",
    "加熱": true,
    "本物の食材": [
      "豚ひき肉",
      "キャベツ",
      "ねぎ",
      "しょうが",
      "餃子の皮"
    ],
    "使える食材カテゴリ": [
      "肉系",
      "野菜系",
      "主食系"
    ],
    "必要調理法": "焼き",
    "加工手順": [
      "キャベツとねぎをみじん切りに",
      "全材料を混ぜて餃子の皮に包む",
      "水を加えて蒸し焼きにする"
    ],
    "説明文": "肉と野菜を皮で包んで焼いた中華の定番。パリっとした皮の食感と肉汁たっぷりの中身が最高で、タレをつけるとやめられない"
  },
  {
    "name": "春雨サラダ",
    "ジャンル": "中華",
    "加熱": true,
    "本物の食材": [
      "春雨",
      "きゅうり",
      "にんじん",
      "ハム"
    ],
    "使える食材カテゴリ": [
      "主食系",
      "野菜系",
      "根菜系",
      "肉系"
    ],
    "必要調理法": "茹でる",
    "加工手順": [
      "春雨を戻して食べやすい長さに切る",
      "きゅうり・にんじん・ハムを千切りに"
    ],
    "説明文": "戻した春雨に野菜とハムを混ぜて酢醤油で和えたサラダ。つるつるした食感とほどよい酸っぱさが食欲を刺激する"
  },
  {
    "name": "豚の角煮",
    "ジャンル": "中華",
    "加熱": true,
    "本物の食材": [
      "豚バラ肉",
      "ねぎ",
      "しょうが"
    ],
    "使える食材カテゴリ": [
      "肉系",
      "野菜系"
    ],
    "必要調理法": "煮込み",
    "加工手順": [
      "豚バラを大きめの一口大に切る",
      "柔らかくなるまでじっくり煮る"
    ],
    "説明文": "豚バラをしょうゆと砂糖でじっくり煮込んだ料理。箸で切れるほど柔らかく、甘辛い煮汁が染みた脂身がとろけるようなおいしさ"
  },
  {
    "name": "エビチリ",
    "ジャンル": "中華",
    "加熱": true,
    "本物の食材": [
      "エビ",
      "ねぎ",
      "しょうが",
      "にんにく"
    ],
    "使える食材カテゴリ": [
      "魚系",
      "野菜系"
    ],
    "必要調理法": "炒め",
    "加工手順": [
      "エビの背わたを取る",
      "ねぎ・しょうが・にんにくをみじん切りに"
    ],
    "説明文": "エビを豆板醤入りのチリソースで炒めた中華料理。プリプリのエビと辛みのあるトマトベースのソースが絶妙にマッチ"
  },
  {
    "name": "ニラ玉",
    "ジャンル": "中華",
    "加熱": true,
    "本物の食材": [
      "ニラ",
      "卵"
    ],
    "使える食材カテゴリ": [
      "野菜系",
      "卵系"
    ],
    "必要調理法": "炒め",
    "加工手順": [
      "ニラを3〜4cmの長さに切る",
      "卵を溶いておく"
    ],
    "説明文": "ニラと卵を炒めた簡単中華。ニラの香りと卵のふわふわ感が合わさって、シンプルなのにしっかり満足できる一品"
  },
  {
    "name": "バンバンジー",
    "ジャンル": "中華",
    "加熱": false,
    "本物の食材": [
      "鶏むね肉",
      "きゅうり",
      "ねぎ"
    ],
    "使える食材カテゴリ": [
      "肉系",
      "野菜系"
    ],
    "必要調理法": "茹でる",
    "加工手順": [
      "鶏肉を茹でて手で細かくほぐす",
      "きゅうりを細切りに"
    ],
    "説明文": "蒸した鶏肉ときゅうりにごまだれをかけた冷菜。淡白な鶏肉に濃厚なごまだれが絡んで、冷たくてさっぱりおいしい"
  },
  {
    "name": "中華スープ",
    "ジャンル": "中華",
    "加熱": true,
    "本物の食材": [
      "卵",
      "ねぎ",
      "わかめ"
    ],
    "使える食材カテゴリ": [
      "卵系",
      "魚系",
      "野菜系"
    ],
    "必要調理法": "煮る",
    "加工手順": [
      "卵を溶いておく",
      "ねぎを小口切りに",
      "最後に溶いた卵を注いでふわっと固める"
    ],
    "説明文": "鶏がらスープに卵をとき入れたシンプルな中華スープ。ふわふわの卵とごま油の香りが優しくて、どんな料理にも合う万能スープ"
  },
  {
    "name": "パッタイ",
    "ジャンル": "エスニック",
    "加熱": true,
    "本物の食材": [
      "ビーフン",
      "エビ",
      "卵",
      "もやし",
      "ねぎ"
    ],
    "使える食材カテゴリ": [
      "主食系",
      "魚系",
      "卵系",
      "野菜系"
    ],
    "必要調理法": "炒め",
    "加工手順": [
      "ビーフンを水で戻す",
      "ねぎを小口切りに",
      "ビーフンと全材料を一緒に炒める"
    ],
    "説明文": "ビーフンをナンプラーと甘辛ソースで炒めたタイの定番麺料理。甘・辛・酸っぱいが絶妙に混ざり合い、ライムを絞るとさらに本格的"
  },
  {
    "name": "グリーンカレー",
    "ジャンル": "エスニック",
    "加熱": true,
    "本物の食材": [
      "鶏肉",
      "なす",
      "ピーマン",
      "ココナッツミルク"
    ],
    "使える食材カテゴリ": [
      "肉系",
      "魚系",
      "野菜系",
      "乳製品系"
    ],
    "必要調理法": "煮込み",
    "加工手順": [
      "鶏肉と野菜を一口大に切る",
      "ココナッツミルクとグリーンカレーのルーを入れる"
    ],
    "説明文": "ハーブたっぷりのタイ風グリーンカレー。ココナッツミルクのまろやかさとハーブの香りが独特で、スパイシーなのにどこか優しい不思議な一品"
  },
  {
    "name": "チャプチェ",
    "ジャンル": "エスニック",
    "加熱": true,
    "本物の食材": [
      "春雨",
      "牛肉",
      "にんじん",
      "ほうれん草",
      "きのこ"
    ],
    "使える食材カテゴリ": [
      "主食系",
      "肉系",
      "根菜系",
      "野菜系"
    ],
    "必要調理法": "炒め",
    "加工手順": [
      "春雨を戻して適当な長さに",
      "牛肉と野菜を細切りに"
    ],
    "説明文": "春雨と野菜・肉をごま油で炒めた韓国料理。つるつるの春雨にごま油の香りが絡んで、甘辛いタレが全体をまとめる上品感"
  },
  {
    "name": "チゲ鍋",
    "ジャンル": "エスニック",
    "加熱": true,
    "本物の食材": [
      "豚肉",
      "豆腐",
      "キムチ",
      "ねぎ",
      "もやし"
    ],
    "使える食材カテゴリ": [
      "肉系",
      "豆・豆腐系",
      "漬物系",
      "野菜系"
    ],
    "必要調理法": "煮込み",
    "加工手順": [
      "豚肉と豆腐を食べやすい大きさに切る",
      "ねぎを斜め切りに"
    ],
    "説明文": "キムチと豆腐を辛いスープで煮込んだ韓国鍋。キムチの酸っぱさと辛みがスープに溶け込んで、体の芯まで温まる冬の定番"
  },
  {
    "name": "ビビンバ",
    "ジャンル": "エスニック",
    "加熱": true,
    "本物の食材": [
      "ご飯",
      "牛肉",
      "ほうれん草",
      "もやし",
      "にんじん"
    ],
    "使える食材カテゴリ": [
      "主食系",
      "肉系",
      "野菜系",
      "根菜系"
    ],
    "必要調理法": "炒め",
    "加工手順": [
      "野菜をそれぞれ茹でて水気を絞る",
      "牛肉を細切りに炒める",
      "ご飯にのせる"
    ],
    "説明文": "ご飯の上に様々なナムルと肉をのせてコチュジャンで混ぜる韓国料理。混ぜるほどに全てがなじんで、カラフルな見た目も楽しい"
  },
  {
    "name": "ガパオライス",
    "ジャンル": "エスニック",
    "加熱": true,
    "本物の食材": [
      "鶏ひき肉",
      "バジル",
      "ピーマン",
      "にんにく",
      "卵",
      "ご飯"
    ],
    "使える食材カテゴリ": [
      "肉系",
      "野菜系",
      "卵系",
      "主食系"
    ],
    "必要調理法": "炒め",
    "加工手順": [
      "ピーマンとにんにくを細かく切る",
      "卵以外の材料を炒めてご飯に乗せる",
      "目玉焼きを作り最後に上に乗せる"
    ],
    "説明文": "鶏肉とバジルをナンプラーで炒め目玉焼きをのせたタイ料理。バジルとナンプラーの香りが食欲をガツンと刺激する"
  },
  {
    "name": "ナシゴレン",
    "ジャンル": "エスニック",
    "加熱": true,
    "本物の食材": [
      "ご飯",
      "エビ",
      "卵",
      "キャベツ",
      "ねぎ"
    ],
    "使える食材カテゴリ": [
      "主食系",
      "魚系",
      "卵系",
      "野菜系"
    ],
    "必要調理法": "炒め",
    "加工手順": [
      "キャベツをざく切りに",
      "ねぎを小口切りに",
      "卵を溶いておく"
    ],
    "説明文": "エビと野菜を炒めたインドネシア風チャーハン。ナンプラーとケチャップマニスの甘辛い香りが食欲をそそる南国の一品"
  },
  {
    "name": "韓国風卵スープ",
    "ジャンル": "エスニック",
    "加熱": true,
    "本物の食材": [
      "卵",
      "ねぎ",
      "えのき"
    ],
    "使える食材カテゴリ": [
      "卵系",
      "野菜系"
    ],
    "必要調理法": "煮る",
    "加工手順": [
      "卵を溶いておく",
      "ねぎを小口切りに",
      "えのきを小分けにする"
    ],
    "説明文": "ふわふわ卵とえのきをごま油で仕上げた韓国風スープ。塩とごま油のやさしい香りがほっとする一杯で、毎日飲みたくなる"
  },
  {
    "name": "サムギョプサル風炒め",
    "ジャンル": "エスニック",
    "加熱": true,
    "本物の食材": [
      "豚バラ肉",
      "ねぎ",
      "サンチュ",
      "にんにく"
    ],
    "使える食材カテゴリ": [
      "肉系",
      "野菜系"
    ],
    "必要調理法": "焼き",
    "加工手順": [
      "豚バラを食べやすい長さに切る",
      "にんにくを薄切りに",
      "サンチュを別皿に添える"
    ],
    "説明文": "豚バラを焼いて野菜に包んで食べる韓国バーベキュー風。脂がのった豚バラとごま塩・コチュジャンの組み合わせが最高"
  },
  {
    "name": "豆腐チゲ風みそ汁",
    "ジャンル": "エスニック",
    "加熱": true,
    "本物の食材": [
      "豆腐",
      "キムチ",
      "豚肉",
      "ねぎ"
    ],
    "使える食材カテゴリ": [
      "豆・豆腐系",
      "漬物系",
      "肉系",
      "野菜系"
    ],
    "必要調理法": "煮る",
    "加工手順": [
      "豆腐を食べやすい大きさに切る",
      "豚肉をひと口大に",
      "ねぎを斜め切りに"
    ],
    "説明文": "キムチと豆腐をみそで煮込んだ和韓折衷スープ。キムチの酸味とみその旨みがうまく合わさって、体があったまる不思議な一杯"
  },
  {
    "name": "あったかスープ",
    "ジャンル": "和食",
    "加熱": true,
    "本物の食材": [
      "野菜",
      "肉",
      "豆腐"
    ],
    "使える食材カテゴリ": [
      "肉系",
      "魚系",
      "野菜系",
      "根菜系",
      "芋系",
      "豆・豆腐系",
      "卵系"
    ],
    "必要調理法": "煮る",
    "加工手順": [
      "具材を適当な大きさに切る"
    ],
    "説明文": "手元にある具材を煮込んで作るスープ。和洋中の何にでもなれる懐の深い料理で、寒い日も体が温まる万能メニュー"
  },
  {
    "name": "あったかうどん",
    "ジャンル": "和食",
    "加熱": true,
    "本物の食材": [
      "うどん"
    ],
    "使える食材カテゴリ": [
      "主食系",
      "肉系",
      "魚系",
      "野菜系",
      "根菜系",
      "卵系"
    ],
    "必要調理法": "煮る",
    "加工手順": [
      "うどんを茹でる",
      "具材を適当な大きさに切る",
      "だし汁で具材を煮込みうどんと合わせる"
    ],
    "説明文": "温かいだしのスープでうどんを食べる料理。卵でもお肉でも野菜でも、何をのせてもおいしくなる受け入れ力の高いメニュー"
  },
  {
    "name": "のっけトースト",
    "ジャンル": "洋食",
    "加熱": true,
    "本物の食材": [
      "食パン"
    ],
    "使える食材カテゴリ": [
      "主食系",
      "肉系",
      "魚系",
      "卵系",
      "乳製品系",
      "野菜系"
    ],
    "必要調理法": "焼き",
    "加工手順": [
      "具材を食べやすい大きさに切ってトーストに乗せる",
      "トースターか電子レンジで温める"
    ],
    "説明文": "食パンに手元の具材をのせてトーストする料理。チーズでもポテサラでも納豆でもなんでもおいしくなる、朝食の万能選手"
  },
  {
    "name": "豚肉のっけ丼",
    "ジャンル": "和食",
    "加熱": true,
    "本物の食材": [
      "ご飯",
      "豚肉"
    ],
    "使える食材カテゴリ": [
      "主食系",
      "肉系"
    ],
    "必要調理法": "炒め",
    "加工手順": [
      "豚肉を一口大に切る",
      "醤油・みりんで甘辛く炒める",
      "ご飯にのせる"
    ],
    "説明文": "甘辛く炒めた豚肉をご飯にのせるだけの丼。豚コマでも薄切りでも何でもうまくなるぞい"
  },
  {
    "name": "中華風野菜あんかけ丼",
    "ジャンル": "中華",
    "加熱": true,
    "本物の食材": [
      "ご飯",
      "白菜",
      "にんじん"
    ],
    "使える食材カテゴリ": [
      "主食系",
      "野菜系"
    ],
    "必要調理法": "炒め煮",
    "加工手順": [
      "野菜を食べやすい大きさに切る",
      "ごま油で炒めて水溶き片栗粉でとろみをつける",
      "ご飯にのせる"
    ],
    "説明文": "野菜を炒めてとろみをつけてご飯にかける中華丼風。冷蔵庫の野菜が何でも主役になれる"
  },
  {
    "name": "煮物のっけ丼",
    "ジャンル": "和食",
    "加熱": true,
    "本物の食材": [
      "ご飯",
      "じゃがいも",
      "にんじん"
    ],
    "使える食材カテゴリ": [
      "主食系",
      "芋系",
      "根菜系"
    ],
    "必要調理法": "煮る",
    "加工手順": [
      "芋・根菜を一口大に切る",
      "醤油・みりん・砂糖で甘辛く煮る",
      "ご飯にのせる"
    ],
    "説明文": "煮物をそのままご飯にのせた丼。ほっこり甘辛い煮汁がご飯に染みてうまい"
  },
  {
    "name": "たまごかけごはん",
    "ジャンル": "和食",
    "加熱": false,
    "本物の食材": [
      "ご飯",
      "卵"
    ],
    "使える食材カテゴリ": [
      "主食系",
      "卵系"
    ],
    "必要調理法": "なし",
    "加工手順": [
      "卵をご飯の上に割り入れる"
    ],
    "説明文": "卵とご飯があれば完成する最速の一品。食べ方もアレンジも無限大。どう転んでもうまいしタンパク質もしっかり取れて健康的。"
  },
  {
    "name": "納豆ごはん",
    "ジャンル": "和食",
    "加熱": false,
    "本物の食材": [
      "ご飯",
      "納豆"
    ],
    "使える食材カテゴリ": [
      "主食系",
      "豆・豆腐系"
    ],
    "必要調理法": "なし",
    "加工手順": [
      "納豆をよくかき混ぜる",
      "付属のタレと辛子を入れる",
      "ご飯にのせる"
    ],
    "説明文": "納豆をご飯にのせるだけで完成する日本の朝食の定番。栄養満点で手間なしの完全食"
  },
  {
    "name": "カレー",
    "ジャンル": "和食",
    "加熱": true,
    "本物の食材": [
      "鶏肉",
      "じゃがいも",
      "玉ねぎ"
    ],
    "使える食材カテゴリ": [
      "肉系",
      "魚系",
      "野菜系",
      "根菜系",
      "芋系"
    ],
    "必要調理法": "煮込み",
    "加工手順": [
      "鶏肉と野菜を一口大に切る",
      "カレーのルーを入れる"
    ],
    "説明文": "家庭料理の大定番。朝から食べられる人も多い。何を入れても何にかけても全てOKの国民食"
  },
  {
    "name": "ステーキ",
    "ジャンル": "洋食",
    "加熱": true,
    "本物の食材": [
      "牛肉",
      "バター"
    ],
    "使える食材カテゴリ": [
      "肉系",
      "魚系"
    ],
    "必要調理法": "焼き",
    "加工手順": [
      "1～2cmくらいの厚さに切る",
      "塩コショウし香ばしく焼く",
      "仕上げにバターを加える"
    ],
    "説明文": "シンプルでどんな材料でもいい感じに仕上がる焼き料理。途中でいろいろ味変させるのも楽しい。"
  },
  {
    "name": "塩焼き",
    "ジャンル": "和食",
    "加熱": true,
    "本物の食材": [
      "アジ"
    ],
    "使える食材カテゴリ": [
      "魚系",
      "肉系"
    ],
    "必要調理法": "焼き",
    "加工手順": [
      "具材に塩を振る",
      "魚焼きグリルかフライパンで焦げ目がつくように焼く"
    ],
    "説明文": "定食屋さんの定番。シンプルでどんな材料でもいい感じに仕上がる焼き料理。余裕があるときは大根おろしも添えたい。"
  }
]